mac_cleanup/__init__.py
mac_cleanup/__version__.py
mac_cleanup/config.py
mac_cleanup/console.py
mac_cleanup/core.py
mac_cleanup/core_modules.py
mac_cleanup/default_modules.py
mac_cleanup/error_handling.py
mac_cleanup/main.py
mac_cleanup/parser.py
mac_cleanup/progress.py
mac_cleanup/utils.py
mac_cleanup-3.3.0.dist-info/LICENSE
mac_cleanup-3.3.0.dist-info/METADATA
mac_cleanup-3.3.0.dist-info/WHEEL
mac_cleanup-3.3.0.dist-info/entry_points.txt
mac_cleanup-3.3.0.dist-info/RECORD
