Metadata-Version: 2.3
Name: mac_cleanup
Version: 3.3.0
Summary: Python cleanup script for macOS
License: Apache-2.0
Keywords: macos,script,cleanup,cleaner
Author: efa2d19
Requires-Python: >=3.10,<3.14
Classifier: Environment :: Console
Classifier: License :: OSI Approved :: Apache Software License
Classifier: Operating System :: MacOS
Classifier: Programming Language :: Python :: 3
Classifier: Programming Language :: Python :: 3.10
Classifier: Programming Language :: Python :: 3.11
Classifier: Programming Language :: Python :: 3.12
Classifier: Programming Language :: Python :: 3.13
Requires-Dist: attrs (>=25.3.0,<25.4.0)
Requires-Dist: beartype (>=0.20.0,<0.21.0)
Requires-Dist: inquirer (>=3.4.0,<4.0.0)
Requires-Dist: rich (>=13.9.4,<14.0.0)
Requires-Dist: toml (>=0.10.2,<0.11.0)
Requires-Dist: xattr (>=1.1.4,<1.2.0)
Project-URL: Documentation, https://github.com/mac-cleanup/mac-cleanup-py#install-automatically
Project-URL: Homepage, https://github.com/mac-cleanup/mac-cleanup-py
Project-URL: Issue Tracker, https://github.com/mac-cleanup/mac-cleanup-py/issues
Project-URL: Repository, https://github.com/mac-cleanup/mac-cleanup-py
